ding/__init__.py
ding/lookup.py
ding/otp.py
ding/sdk.py
ding/sdkconfiguration.py
ding/_hooks/__init__.py
ding/_hooks/sdkhooks.py
ding/_hooks/types.py
ding/models/__init__.py
ding/models/components/__init__.py
ding/models/components/authenticationstatusresponse.py
ding/models/components/checkstatus.py
ding/models/components/createauthenticationrequest.py
ding/models/components/createauthenticationresponse.py
ding/models/components/createcheckrequest.py
ding/models/components/createcheckresponse.py
ding/models/components/feedbackrequest.py
ding/models/components/feedbackresponse.py
ding/models/components/lookupresponse.py
ding/models/components/retryauthenticationrequest.py
ding/models/components/retryauthenticationresponse.py
ding/models/components/security.py
ding/models/errors/__init__.py
ding/models/errors/errorresponse.py
ding/models/errors/sdkerror.py
ding/models/operations/__init__.py
ding/models/operations/check.py
ding/models/operations/create_authentication.py
ding/models/operations/feedback.py
ding/models/operations/getauthenticationstatus.py
ding/models/operations/lookup.py
ding/models/operations/retry.py
ding/utils/__init__.py
ding/utils/retries.py
ding/utils/utils.py
ding_api_client-3.9.120.dist-info/METADATA
ding_api_client-3.9.120.dist-info/WHEEL
ding_api_client-3.9.120.dist-info/top_level.txt
ding_api_client-3.9.120.dist-info/RECORD
